clwcli/__init__.py
clwcli/__main__.py
clwcli/cli.py
clwcli/utils.py
clwcli-0.1.0.dist-info/DESCRIPTION.rst
clwcli-0.1.0.dist-info/METADATA
clwcli-0.1.0.dist-info/RECORD
clwcli-0.1.0.dist-info/WHEEL
clwcli-0.1.0.dist-info/entry_points.txt
clwcli-0.1.0.dist-info/metadata.json
clwcli-0.1.0.dist-info/top_level.txt
